infrafm/__init__.py
infrafm/charter.py
infrafm/client.py
infrafm/exceptions.py
infrafm/py.typed
infrafm/utils.py
infrafm/api/__init__.py
infrafm/api/album.py
infrafm/api/artist.py
infrafm/api/chart.py
infrafm/api/geo.py
infrafm/api/tag.py
infrafm/api/track.py
infrafm/api/user.py
infrafm/models/__init__.py
infrafm/models/album.py
infrafm/models/artist.py
infrafm/models/base.py
infrafm/models/tag.py
infrafm/models/track.py
infrafm/models/user.py
infrared_fm-2.3.0.dist-info/licenses/LICENSE
infrared_fm-2.3.0.dist-info/METADATA
infrared_fm-2.3.0.dist-info/WHEEL
infrared_fm-2.3.0.dist-info/top_level.txt
infrared_fm-2.3.0.dist-info/RECORD
