Metadata-Version: 2.4
Name: infrared-fm
Version: 2.3.0
Summary: Last.FM wrapper by Infrared LLC.
Home-page: https://github.com/infraredhuh/infrared-fm
Author: infrared
Author-email: faneorg.official@gmail.com
Classifier: Programming Language :: Python :: 3
Classifier: License :: OSI Approved :: MIT License
Classifier: Operating System :: OS Independent
Classifier: Typing :: Typed
Requires-Python: >=3.8
License-File: LICENSE
Requires-Dist: aiohttp>=3.9.0
Requires-Dist: pillow<10.0.0,>=9.0.0
Dynamic: author
Dynamic: author-email
Dynamic: classifier
Dynamic: description
Dynamic: description-content-type
Dynamic: home-page
Dynamic: license-file
Dynamic: requires-dist
Dynamic: requires-python
Dynamic: summary
